{
  "version": 1,
  "generatedAt": "2026-06-10T19:55:35.578Z",
  "phrases": {
    "rammstein": "褉+邪屑褕褌+邪泄薪",
    "du hast": "写+褍 褏+邪褋褌",
    "engel": "+褝薪谐械谢褜",
    "tier": "褌+懈褉",
    "bestrafe mich": "斜+械褋褌褉邪褎械 屑+懈褏",
    "b眉ck dich": "斜+褞泻 写+懈褏",
    "spiel mit mir": "褕锌+懈谢褜 屑懈褌 屑+懈褉",
    "klavier": "泻谢邪胁+懈褉",
    "eifersucht": "+邪泄褎械褉蟹褍褏褌",
    "k眉ss mich (fellfrosch)": "泻+褞褋 屑+懈褏",
    "sehnsucht": "蟹+械薪蟹褍褏褌",
    "wollt ihr das bett in flammen sehen?": "胁芯谢褌 懈+懈褉 写邪褋 斜+械褌 懈薪 褎谢+邪屑屑械薪 蟹+械械薪",
    "der meister": "写+械褉 屑+邪泄褋褌械褉",
    "weisses fleisch": "胁+邪泄褋械褋 褎谢+邪泄褕",
    "asche zu asche": "+邪褕械 褑褍 +邪褕械",
    "seemann": "蟹+械屑邪薪",
    "du riechst so gut": "写+褍 褉+懈褏褋褌 蟹芯 谐+褍褌",
    "das alte leid": "写+邪褋 +邪谢褜褌械 谢+邪泄写",
    "heirate mich": "褏+邪泄褉邪褌械 屑+懈褏",
    "herzeleid": "褏+械褉褑械谢邪泄写",
    "laichzeit": "谢+邪泄褏褑邪泄褌",
    "links 2 3 4": "谢懈薪泻褋 褑胁+邪泄 写褉+邪泄 褎+懈褉",
    "sonne": "蟹+芯薪薪械",
    "ich will": "懈褏 胁+懈谢谢褜",
    "feuer frei!": "褎+芯泄械褉 褎褉+邪泄",
    "feuer frei": "褎+芯泄械褉 褎褉+邪泄",
    "mutter": "屑+褍褌褌械褉",
    "spieluhr": "褕锌+懈谢褍褉",
    "zwei liebeslieder": "褑胁+邪泄 谢+懈斜械褋谢懈写械褉",
    "amour": "邪屑+褍褉",
    "nebel": "薪+械斜械谢褜",
    "halleluja": "褏+邪谢械谢褍褟",
    "reise, reise": "褉+邪泄蟹械 褉+邪泄蟹械",
    "reise reise": "褉+邪泄蟹械 褉+邪泄蟹械",
    "mein teil": "屑+邪泄薪 褌+邪泄谢褜",
    "dalai lama": "写+邪谢邪泄 谢+邪屑邪",
    "amerika": "邪屑+械褉懈泻邪",
    "moskau": "屑+芯褋泻邪褍",
    "ohne dich": "+芯薪械 写+懈褏",
    "keine lust": "泻+邪泄薪械 谢+褍褋褌",
    "los": "谢+芯褋",
    "donnerschlag": "写+芯薪薪械褉褕谢邪谐",
    "morgenstern": "屑+芯褉谐械薪褕tern",
    "rosenrot": "褉+芯蟹械薪褉芯褌",
    "mann gegen mann": "屑+邪薪薪 谐+械谐械薪 屑+邪薪薪",
    "wo bist du?": "胁芯 斜+懈褋褌 写+褍",
    "wo bist du": "胁芯 斜+懈褋褌 写+褍",
    "zerst枚ren": "褑械褉褋褌+褢褉械薪",
    "stirb nicht vor mir": "褕褌+懈褉斜 薪+懈褏褌 褎芯褉 屑+懈褉",
    "te quiero puta!": "褌械 泻+iero 锌+褍褌邪",
    "hilf mir": "褏+懈谢褎 屑+懈褉",
    "rammlied": "褉+邪屑屑谢懈写",
    "ich tu dir weh": "懈褏 褌褍 写+懈褉 胁+械",
    "waidmanns heil": "胁+邪泄写屑邪薪褋 褏+邪泄谢褜",
    "haifisch": "褏+邪泄褎懈褕",
    "b眉ckst du": "斜+褞泻褋褌 写+褍",
    "fr眉hling in paris": "褎褉+褞谢懈薪谐 懈薪 锌邪褉+懈褋",
    "deutschland": "写+芯泄褔谢邪薪写",
    "radio": "褉+邪写懈芯",
    "zeig dich": "褑+邪泄谐 写+懈褏",
    "ausl盲nder": "+邪褍褋谢械薪写械褉",
    "auslander": "+邪褍褋谢械薪写械褉",
    "sex": "蟹+械泻褋",
    "puppe": "锌+褍锌锌械",
    "was ich liebe": "胁+邪褋 懈褏 谢+懈斜械",
    "diamant": "写懈邪屑+邪薪褌",
    "zeit": "褑+邪泄褌",
    "adieu": "邪写+褜褢",
    "l眉gen": "谢+褞谐械薪",
    "armee der verlierer": "邪褉屑+械械 写械褉 褎+械褉谢懈褉械褉",
    "deutschland 眉ber alles": "写+芯泄褔谢邪薪写 +眉ber +邪谢谢械褋",
    "mein herz brennt": "屑+邪泄薪 褏+械褉褑 斜褉+械薪褌",
    "pussy": "锌+褍褋褋懈",
    "mein land": "屑+邪泄薪 谢+邪薪褌",
    "till lindemann": "褌+懈谢谢褜 谢+懈薪写械屑邪薪薪",
    "richard kruspe": "褉+懈褏邪褉写 泻褉+褍褋锌械",
    "paul landers": "锌邪+褍谢褜 谢+邪薪写械褉褋",
    "oliver riedel": "+芯谢iver 褉+懈写械谢褜",
    "christoph schneider": "泻褉+懈褋褌芯褎 褕薪+邪泄写械褉",
    "christian lorenz": "泻褉+懈褋褌懈邪薪 谢+芯褉械薪褑",
    "flake lorenz": "褎谢+械泄泻 谢+芯褉械薪褑",
    "scorpions": "褋泻+芯褉锌懈芯薪褋",
    "kraftwerk": "泻褉+邪褎褌胁械褉泻",
    "nena": "薪+械薪邪",
    "99 luftballons": "薪邪泄薪褍芯泄薪褑懈褏 谢+褍褎褌斜邪谢芯薪褋",
    "99 red balloons": "薪邪泄薪褍芯泄薪褑懈褏 谢+褍褎褌斜邪谢芯薪褋",
    "nur getr盲umt": "薪+褍褉 谐械褌褉+枚m褌",
    "die toten hosen": "写懈 褌+芯褌械薪 褏+芯蟹械薪",
    "tote hosen": "褌+芯褌械薪 褏+芯蟹械薪",
    "die 盲rzte": "写懈 +褝褉褑褌械",
    "die arzte": "写懈 +褝褉褑褌械",
    "herbert gr枚nemeyer": "谐褉+褢薪械屑邪泄械褉",
    "herbert gronemeyer": "谐褉+褢薪械屑邪泄械褉",
    "xavier naidoo": "泻褋+邪胁褜械褉 薪+邪泄写褍",
    "peter maffay": "锌+械褌械褉 屑邪ff+邪泄",
    "tokio hotel": "褌+芯泻懈芯 褏芯褌+械谢褜",
    "modern talking": "屑+芯写械褉薪 褌+芯泻懈薪谐",
    "sandra": "蟹+邪薪写褉邪",
    "alphaville": "+邪谢褜褎邪胁懈谢谢械",
    "forever young": "褎芯褉+械胁械褉 褟+薪谐",
    "big in japan": "斜+懈谐 懈薪 写卸+邪锌邪薪",
    "scooter": "褋泻+褍褌械褉",
    "how much is the fish?": "褏+邪褍 屑+邪褔 懈蟹 蟹+械 fish",
    "paul van dyk": "锌邪+褍谢褜 褎邪薪 写+邪泄泻",
    "atb": "邪-褌械-斜械",
    "9 pm (till i come)": "薪邪泄薪 锌+懈-褝屑",
    "wir sind helden": "胁+懈褉 蟹+懈薪写 褏+械谢褜写械薪",
    "silbermond": "蟹+懈谢褜斜械褉屑芯薪写",
    "annenmaykantereit": "+annen 屑邪泄 泻邪薪褌+械褉械泄褌",
    "revolverheld": "褉械胁芯谢+褜胁械褉褏械谢褜写",
    "seeed": "褋+懈写",
    "sido": "蟹+懈写芯",
    "peter fox": "锌+械褌械褉 褎+芯泻褋",
    "alle neuen fahren schwarz": "+邪谢谢械 薪+芯泄械薪 褎+邪褉械薪 褕胁+邪褉褑",
    "die prinzen": "写懈 锌褉+懈薪褑械薪",
    "alles nur geklaut": "+邪谢谢械褋 薪+褍褉 谐械泻谢+邪褍褌",
    "helene fischer": "褏+械谢械薪械 褎+懈褕械褉",
    "atemlos durch die nacht": "+邪褌械屑谢芯褋 写+褍褉褏 写懈 薪+邪褏褌",
    "udo lindenberg": "+褍写芯 谢+懈薪写械薪斜械褉谐",
    "sportfreunde stiller": "褕锌+芯褉褌褎褉芯泄薪写械 褕褌+懈谢谢械褉",
    "54, 74, 90, 2010": "褎+眉nfundf眉nfzig vierundsiebzig neunzig zweitausendzehn",
    "applaus applaus": "邪锌谢+邪褍褋 邪锌谢+邪褍褋",
    "unheilig": "+褍薪褏邪泄谢懈褏",
    "geboren um zu leben": "geb+oren 褍屑 褑褍 谢+械斜械薪",
    "eisbrecher": "+邪泄褋斜褉械褏械褉",
    "oomph": "褍屑褎",
    "in extremo": "懈薪 褝泻褋褌褉+械屑芯",
    "faun": "褎+邪褍薪",
    "megaherz": "屑+械谐邪褏械褉褑",
    "milky chance": "屑+懈谢泻懈 褔+邪薪褋",
    "stolen dance": "褋褌+芯褍谢械薪 写+邪薪褋",
    "cascada": "泻+邪褋泻邪写邪",
    "everytime we touch": "+everytime 胁懈 褌+邪褔",
    "fancy": "褎+褝薪褋懈",
    "flames of love": "褎谢+械泄屑褋 芯胁 谢+邪胁",
    "boney m.": "斜+芯褍薪懈 褝屑",
    "boney m": "斜+芯褍薪懈 褝屑",
    "daddy cool": "写+褝写写懈 泻+褍谢",
    "rivers of babylon": "褉+懈胁械褉褋 芯胁 斜+邪斜懈谢芯薪",
    "kraftklub": "泻褉+邪褎褌泻谢褍斜",
    "beatsteaks": "斜+懈褌褋褌+懈泻褋",
    "mark forster": "屑+邪褉泻 褎+芯褉褋褌械褉",
    "marius m眉ller-westernhagen": "屑+邪褉懈褍褋 屑+褞谢谢械褉-胁械褋褌+械褉薪褏邪谐械薪",
    "westernhagen": "胁械褋褌+械褉薪褏邪谐械薪",
    "nina hagen": "薪+懈薪邪 褏+邪谐械薪",
    "einst眉rzende neubauten": "+邪泄薪褕褌+眉r褑械薪写械 薪+芯泄斜邪褍褌械薪",
    "feuerschwanz": "褎+芯泄械褉褕胁邪薪褑",
    "saltatio mortis": "蟹+邪谢褜褌邪褑懈芯 屑+芯褉褌懈褋",
    "h-blockx": "褏-斜谢+芯泻褋",
    "j.b.o.": "写卸械-斜+械-芯",
    "gentleman": "写卸+械薪褌谢褜屑邪薪",
    "kool savas": "泻+褍谢 褋邪胁+邪褋",
    "lafee": "谢+邪褎械",
    "luciano": "谢+褍褔懈邪薪芯",
    "madsen": "屑+邪写褋械薪",
    "mantar": "屑+邪薪褌邪褉",
    "massiv": "屑+邪褋褋懈胁",
    "mousse t.": "屑+褍褋褋械 褌+械",
    "philipp poisel": "褎+懈谢懈锌锌 锌+芯泄蟹械谢褜",
    "rainhard fendrich": "褉+邪泄薪褏邪褉写 褎+械薪写褉懈褏",
    "wanda": "胁+邪薪写邪",
    "gregorian": "谐褉械谐+芯褉懈邪薪",
    "jamule": "写卸+邪屑褍谢械",
    "joris": "泄+芯褉懈褋",
    "juli": "泄+褍谢懈",
    "kissin' dynamite": "泻+懈褋褋懈薪 写+邪泄namite",
    "klee": "泻谢+械",
    "lary": "谢+邪褉懈",
    "matz wagemann": "屑+邪褑 胁+邪谐emann",
    "no angels": "薪芯 +邪薪谐械谢褋",
    "rosenstolz": "褉+芯蟹械薪褕褌+芯谢褜褑",
    "strassenjungs": "褕褌褉+邪褋褋械薪泄+褍薪谐褋",
    "freundeskreis": "褎褉+芯泄薪写械褋泻褉邪泄褋",
    "falco": "褎+邪谢褜泻芯",
    "rock me amadeus": "褉+芯泻 屑懈 邪屑+邪写械褍褋",
    "der kommissar": "写+械褉 泻芯屑+懈褋褋邪褉",
    "m眉nchener freiheit": "屑+褞nchener 褎褉+邪泄褏邪泄褌",
    "ohne dich (schlager)": "+芯薪械 写+懈褏",
    "lucilectric": "谢+褍褑懈谢械泻褌褉懈泻",
    "m枚nkey business": "屑+枚nkey 斜+懈蟹薪械褋",
    "dynamite deluxe": "写+邪泄namite 写械谢+褞泻褋",
    "die fantastischen vier": "写懈 褎邪薪褌邪褋褌+ischen 褎+懈褉",
    "fettes brot": "褎+械褌褌械褋 斜褉+芯褌",
    "beginner": "斜械谐+懈薪薪械褉",
    "cascadeur": "泻邪褋泻邪写+褢褉",
    "deichkind": "写+邪泄chkind",
    "frittenbude": "褎褉+懈褌褌械薪斜褍写械",
    "k.I.Z.": "泻+邪泄-褑+械褌",
    "kiz": "泻+邪泄-褑+械褌",
    "marteria": "屑+邪褉褌械褉懈褟",
    "prinz pi": "锌褉+懈薪褑 锌+懈",
    "samy delux": "蟹+邪屑懈 写械谢+褞泻褋",
    "shindy": "褕+懈薪写懈",
    "trettmann": "褌褉+械褌褌屑邪薪",
    "ufo361": "褍-褎+芯-361",
    "capital bra": "泻+邪锌懈褌邪谢 斜褉+邪",
    "bonez mc": "斜+芯薪械蟹 褝屑-褑+械",
    "raf camora": "褉+邪褎 泻邪屑+芯褉邪",
    "apache 207": "邪锌+邪褔械 207",
    "badm贸mzjay": "斜+邪写屑芯屑写卸+械泄",
    "loredana": "谢芯褉械写+邪薪邪",
    "cro": "褑褉+芯",
    "alligatoah": "+邪谢谢懈谐atoah",
    "autobahn": "+邪褍褌芯斜邪薪",
    "das model": "写+邪褋 屑+芯写械谢褜",
    "trans-europe express": "褌褉+邪薪褋-械胁褉+芯锌械 褝泻褋锌褉+械褋褋",
    "the robots": "蟹械 褉+芯斜芯褌褋",
    "computer world": "泻芯屑锌+褜褞褌械褉 胁+褢褉谢写",
    "musique non stop": "屑+褞蟹懈泻 薪+芯薪 褋褌+芯锌",
    "wind of change": "胁+懈薪写 芯胁 褔+械泄薪写卸",
    "still loving you": "褋褌+懈谢谢 谢+邪胁懈薪谐 褞",
    "rock you like a hurricane": "褉+芯泻 褞 谢+邪泄泻 邪 褏+邪褉ricane",
    "send me an angel": "褋+械薪写 屑懈 +an +angel",
    "big city nights": "斜+懈谐 褋+懈褌懈 薪邪泄褌褋",
    "no one like you": "薪芯 +one 谢+邪泄泻 褞",
    "(i'll never be) maria magdalena": "mar+ia magdal+ena",
    "durch den monsoon": "写+褍褉褏 写械薪 屑芯薪+褍薪",
    "ready, set, go!": "褉+械写懈 褋+械褌 谐+芯",
    "monsoon": "屑+芯薪soon",
    "automatic": "+邪胁褌芯屑邪褌懈泻"
  },
  "words": {
    "und": "褍薪写",
    "der": "写+械褉",
    "die": "写+懈",
    "das": "写+邪褋",
    "ein": "+邪泄薪",
    "eine": "+邪泄薪械",
    "einer": "+邪泄薪械褉",
    "dem": "写+械屑",
    "den": "写+械薪",
    "des": "写+械褋",
    "im": "懈屑",
    "am": "邪屑",
    "zum": "褑+褍屑",
    "zur": "褑+褍褉",
    "mit": "屑+懈褌",
    "von": "褎+芯薪",
    "aus": "+邪褍褋",
    "bei": "斜+邪泄",
    "nach": "薪+邪褏",
    "vor": "褎+芯褉",
    "眉ber": "+眉ber",
    "unter": "+褍薪ter",
    "durch": "写+褍褉褏",
    "ohne": "+芯薪械",
    "gegen": "谐+械谐械薪",
    "zwischen": "褑胁+懈褕械薪",
    "ich": "懈褏",
    "du": "写+褍",
    "er": "+械褉",
    "sie": "蟹+懈",
    "es": "+械褋",
    "wir": "胁+懈褉",
    "ihr": "懈+懈褉",
    "sie_plural": "蟹+懈",
    "nicht": "薪+懈褏褌",
    "ist": "懈褋褌",
    "sind": "蟹+懈薪写",
    "war": "胁+邪褉",
    "hat": "褏+邪褌",
    "haben": "褏+邪斜械薪",
    "hast": "褏+邪褋褌",
    "bin": "斜+懈薪",
    "bist": "斜+懈褋褌",
    "wird": "胁+懈褉写",
    "kann": "泻+邪薪薪",
    "will": "胁+懈谢谢褜",
    "mich": "屑+懈褏",
    "dich": "写+懈褏",
    "sich": "蟹+懈褏",
    "mein": "屑+邪泄薪",
    "dein": "写+邪泄薪",
    "sein": "蟹+邪泄薪",
    "uns": "+褍薪褋",
    "euch": "+芯泄褏",
    "man": "屑+邪薪薪",
    "auch": "+邪褍褏",
    "nur": "薪+褍褉",
    "noch": "薪+芯褏",
    "schon": "褕+芯薪",
    "sehr": "蟹+械褉",
    "gut": "谐+褍褌",
    "mehr": "屑+械褉",
    "wenig": "胁+械薪懈谐",
    "alle": "+邪谢谢械",
    "alles": "+邪谢谢械褋",
    "kein": "泻+邪泄薪",
    "keine": "泻+邪泄薪械",
    "keinen": "泻+邪泄薪械薪",
    "lust": "谢+褍褋褌",
    "herz": "褏+械褉褑",
    "brennt": "斜褉+械薪褌",
    "liebe": "谢+懈斜械",
    "leben": "谢+械斜械薪",
    "tod": "褌+芯写",
    "nacht": "薪+邪褏褌",
    "tag": "褌+邪谐",
    "zeit": "褑+邪泄褌",
    "welt": "胁+械谢褜褌",
    "land": "谢+邪薪褌",
    "stadt": "褕褌+邪写褌",
    "mensch": "屑+械薪褕",
    "kind": "泻+懈薪写",
    "frau": "褎褉+邪褍",
    "mann": "屑+邪薪薪",
    "jung": "泄+褍薪谐",
    "alt": "+邪谢褜褌",
    "neu": "薪+芯泄",
    "gro脽": "谐褉+芯",
    "klein": "泻谢+邪泄薪",
    "sch枚n": "褕+枚n",
    "frei": "褎褉+邪泄",
    "wahr": "胁+邪褉",
    "wahrheit": "胁+邪褉褏邪泄褌",
    "feuer": "褎+芯泄er",
    "wasser": "胁+邪褋褋械褉",
    "sonne": "蟹+芯薪ne",
    "mond": "屑+芯薪写",
    "stern": "褕褌+械褉薪",
    "wo": "胁芯",
    "was": "胁+邪褋",
    "wer": "胁+械褉",
    "wie": "胁+懈",
    "wann": "胁+邪薪",
    "warum": "胁邪褉+褍屑",
    "hier": "褏+懈褉",
    "dort": "写+芯褉褌",
    "heute": "褏+芯泄褌械",
    "morgen": "屑+芯褉谐械薪",
    "gestern": "谐+械褋褌ern",
    "immer": "+懈屑屑械褉",
    "nie": "薪+懈",
    "vielleicht": "褎+懈谢谢邪泄褏褌",
    "viel": "褎+懈谢褜",
    "zwei": "褑胁+邪泄",
    "drei": "写褉+邪泄",
    "vier": "褎+懈褉",
    "f眉nf": "褎+眉n褎",
    "sechs": "蟹+械泻褋",
    "sieben": "蟹+懈斜械薪",
    "acht": "+邪褏褌",
    "neun": "薪+芯泄薪",
    "zehn": "褑+械薪",
    "hundert": "褏+褍薪dert",
    "tausend": "褌+邪褍蟹end",
    "links": "谢懈薪泻褋",
    "rechts": "褉+械褏褌褋",
    "auf": "+auf",
    "ab": "+邪斜",
    "an": "+邪薪",
    "zu": "褑+褍",
    "um": "+褍屑",
    "so": "蟹+芯",
    "ganz": "谐+邪薪褑",
    "fast": "褎+邪褋褌",
    "bald": "斜+邪谢褜写",
    "lass": "谢+邪褋",
    "mach": "屑+邪褏",
    "geh": "谐+械",
    "komm": "泻+芯屑",
    "sieh": "蟹+懈",
    "h枚r": "褏+褢褉",
    "tanz": "褌+邪薪褑",
    "sing": "蟹+懈薪谐",
    "spiel": "褕锌+懈谢褜",
    "bleib": "斜谢+邪泄斜",
    "gib": "谐+懈斜",
    "nimm": "薪+懈屑",
    "halt": "褏+邪谢褜褌",
    "steh": "褕褌+械",
    "fall": "褎+邪谢褜",
    "lauf": "谢+auf",
    "fahr": "褎+邪褉",
    "flieg": "褎谢+懈",
    "schrei": "褕褉+邪泄",
    "wein": "胁+邪泄薪",
    "lach": "谢+邪褏",
    "schlaf": "褕谢+邪褎",
    "tr盲um": "褌褉+枚m",
    "brenn": "斜褉+械薪",
    "brenne": "斜褉+械薪薪械",
    "leuchte": "谢+芯泄褏褌械",
    "leuchtet": "谢+芯泄褏tet",
    "verlierer": "褎+械褉谢懈褉er",
    "verlier": "褎+械褉谢懈褉",
    "gewinner": "谐械胁+懈薪薪械褉"
  },
  "artistKeys": [
    "accept",
    "alligatoah",
    "alphaville",
    "annen may kantereit",
    "annenmaykantereit",
    "apache 207",
    "asp",
    "atb",
    "avantasia",
    "badm贸mzjay",
    "beatsteaks",
    "beginner",
    "blind guardian",
    "boney m",
    "boney m.",
    "bonez mc",
    "capital bra",
    "cascada",
    "christian lorenz",
    "christoph schneider",
    "cro",
    "deichkind",
    "die arzte",
    "die fantastischen vier",
    "die prinzen",
    "die toten hosen",
    "die 盲rzte",
    "dynamite deluxe",
    "edguys",
    "einst眉rzende neubauten",
    "eisbrecher",
    "falco",
    "fancy",
    "faun",
    "fettes brot",
    "feuerschwanz",
    "flake lorenz",
    "freundeskreis",
    "frittenbude",
    "gamma ray",
    "gentleman",
    "grave digger",
    "gregorian",
    "h-blockx",
    "haggard",
    "hammerfall",
    "helene fischer",
    "helloween",
    "herbert gronemeyer",
    "herbert gr枚nemeyer",
    "in extremo",
    "j.b.o.",
    "jamule",
    "joris",
    "juli",
    "k.i.z.",
    "kissin' dynamite",
    "kiz",
    "klee",
    "kool savas",
    "kraftklub",
    "kraftwerk",
    "lacrimosa",
    "lafee",
    "lary",
    "leaves eyes",
    "loredana",
    "luciano",
    "lucilectric",
    "madsen",
    "mantar",
    "marius m眉ller-westernhagen",
    "mark forster",
    "marteria",
    "massiv",
    "matz wagemann",
    "megaherz",
    "milky chance",
    "modern talking",
    "mousse t.",
    "m眉nchener freiheit",
    "nena",
    "nina hagen",
    "no angels",
    "oliver riedel",
    "oomph",
    "oomph!",
    "paul landers",
    "paul van dyk",
    "peter fox",
    "peter maffay",
    "philipp poisel",
    "powerwolf",
    "prinz pi",
    "raf camora",
    "rainhard fendrich",
    "rammstein",
    "revolverheld",
    "richard kruspe",
    "rosenstolz",
    "running wild",
    "saltatio mortis",
    "samy delux",
    "sandra",
    "schandmaul",
    "scooter",
    "scorpions",
    "seeed",
    "shindy",
    "sido",
    "silbermond",
    "sportfreunde stiller",
    "subway to sally",
    "till lindemann",
    "tokio hotel",
    "tote hosen",
    "trettmann",
    "udo lindenberg",
    "ufo361",
    "unheilig",
    "wanda",
    "westernhagen",
    "wir sind helden",
    "xandria",
    "xavier naidoo"
  ]
}